rivalite/__init__.py
rivalite/core.py
rivalite/os_shortcuts.py
rivalite-0.3.0.dist-info/licenses/LICENSE
rivalite-0.3.0.dist-info/METADATA
rivalite-0.3.0.dist-info/WHEEL
rivalite-0.3.0.dist-info/top_level.txt
rivalite-0.3.0.dist-info/RECORD
