Metadata-Version: 2.4
Name: rivalite
Version: 0.3.0
Summary: A collection of helper functions for Python projects.
Author-email: Eric <eric.jiyu.wang@gmail.com>
License: MIT
Project-URL: Homepage, https://github.com/Xplosion257/Rivalite
Project-URL: Repository, https://github.com/Xplosion257/Rivalite
Project-URL: Issues, https://github.com/Xplosion257/Rivalite/issues
Keywords: helpers,utilities,python
Classifier: Programming Language :: Python :: 3
Classifier: License :: OSI Approved :: MIT License
Classifier: Operating System :: OS Independent
Requires-Python: >=3.9
License-File: LICENSE
Dynamic: license-file
